{"meta": {"schema": "https://raw.githubusercontent.com/sdmx-twg/sdmx-json/develop/metadata-message/tools/schemas/1.0/sdmx-json-metadata-schema.json", "id": "1666603382933", "prepared": "2022-10-24T11:23:02Z", "sender": {"id": "MDM"}, "receivers": [], "links": []}, "data": {"metadataSets": [{"id": "MDS_DEFCAU", "publicationPeriod": "Marzo", "names": {"es": "Estad\u00c3\u00adsticas de defunciones por causas de Andaluc\u00c3\u00ada"}, "annotations": [{"id": "MetadataflowId", "texts": {"en": "MDF_DEFCAU"}, "text": "MDF_DEFCAU"}, {"id": "MetadataflowAgency", "texts": {"en": "ESC01"}, "text": "ESC01"}, {"id": "MetadataflowVersion", "texts": {"en": "1.0"}, "text": "1.0"}, {"id": "MSDId", "texts": {"en": "MSD_IECA"}, "text": "MSD_IECA"}, {"id": "MSDAgency", "texts": {"en": "ESC01"}, "text": "ESC01"}, {"id": "MSDVersion", "texts": {"en": "1.0"}, "text": "1.0"}], "links": [{"rel": "msd", "urn": "urn:sdmx:org.sdmx.infomodel.metadatastructure.MetadataStructure=ESC01:MSD_IECA(1.0)"}], "reports": [{"id": "REPORT_EPA", "target": {"id": "MetadataTarget", "referenceValues": [{"id": "DATAFLOW", "object": "urn:sdmx:org.sdmx.infomodel.datastructure.Dataflow=ESC01:DF_DEFCAU4_COVID_LUGAR_MES_SEX(1.1)"}]}, "attributeSet": {"reportedAttributes": [{"id": "A", "attributeSet": {"reportedAttributes": [{"id": "R1", "texts": {"es": "Instituto%20de%20Estad%C3%ADstica%20y%20Cartograf%C3%ADa%20de%20Andaluc%C3%ADa"}}, {"id": "R2", "texts": {"es": "Servicio%20de%20Difusi%C3%B3n%20y%20Publicaciones"}}, {"id": "R3", "texts": {"es": "--"}}, {"id": "R4", "texts": {"es": "Atenci%C3%B3n%20a%20la%20demanda%20de%20informaci%C3%B3n"}}, {"id": "R5", "texts": {"es": "Pabell%C3%B3n%20de%20Nueva%20Zelanda.%20C%2F%20Leonardo%20Da%20Vinci%2C%20n%C2%BA%2021.%20Isla%20de%20La%20Cartuja.%2041071%20-%20Sevilla"}}, {"id": "R6", "texts": {"es": "informacion.ieca%40juntadeandalucia.es"}}, {"id": "R7", "texts": {"es": "Atenci%C3%B3n%20al%20p%C3%BAblico%3A%20900%20101%20407%20Centralita%3A%20955%20033%20800"}}, {"id": "R8", "texts": {"es": "955%20033%20816%2F17"}}]}}, {"id": "B", "attributeSet": {"reportedAttributes": [{"id": "R9", "texts": {"es": "16%2F12%2F2021"}}, {"id": "R10", "texts": {"es": "27%2F05%2F2022"}}, {"id": "R11", "texts": {"es": "27%2F05%2F2022"}}]}}, {"id": "C", "attributeSet": {"reportedAttributes": [{"id": "R12", "texts": {"es": "%3Cp%20style%3D%22text-align%3Ajustify%22%3ELos%20sucesivos%20planes%20estad%26iacute%3Bsticos%20han%20contemplado%20entre%20sus%20objetivos%20el%20mejorar%20el%20conocimiento%20de%20la%20realidad%20de%20la%20Comunidad%20Aut%26oacute%3Bnoma%2C%20as%26iacute%3B%20como%20su%20evoluci%26oacute%3Bn%2C%20en%20sus%20diferentes%20perfiles%20y%20aspectos.%3Cbr%20%2F%3E%0APara%20la%20consecuci%26oacute%3Bn%20de%20este%20objetivo%20se%20plantean%20diversas%20estrategias%2C%20desarrolladas%20a%20trav%26eacute%3Bs%20de%20las%20actividades%20estad%26iacute%3Bsticas%20encuadradas%20en%20las%20diferentes%20%26aacute%3Breas%20de%20los%20planes%20estad%26iacute%3Bsticos.%20Entre%20ellas%20siempre%20se%20ha%20se%26ntilde%3Balado%20el%20profundizar%20en%20el%20conocimiento%20del%20mercado%20de%20trabajo%20andaluz%20y%20de%20sus%20tendencias%2C%20estableciendo%20un%20sistema%20de%20informaci%26oacute%3Bn%20con%20el%20fin%20de%20disponer%20de%20una%20base%20de%20datos%20adecuada%20para%20los%20diferentes%20usuarios.%20Este%20sistema%20debe%20responder%20a%20las%20necesidades%20de%20medici%26oacute%3Bn%20de%20los%20aspectos%20socioecon%26oacute%3Bmicos%20relacionados%20con%20este%20%26aacute%3Bmbito%2C%20tanto%20de%20car%26aacute%3Bcter%20general%20como%20espec%26iacute%3Bficos%3A%20recursos%20humanos%20disponibles%20y%20no%20utilizados%2C%20situaci%26oacute%3Bn%20de%20los%20hogares%2C%20cualificaci%26oacute%3Bn%20y%20formaci%26oacute%3Bn%20profesional%2C%20ajustes%20y%20desajustes%20del%20empleo%20de%20los%20ocupados%2C%20jornadas%20laborales%2C%20cobertura%20de%20prestaciones%3Cbr%20%2F%3E%0AEsta%20medici%26oacute%3Bn%20permitir%26aacute%3B%20la%20detecci%26oacute%3Bn%20de%20los%20puntos%20d%26eacute%3Bbiles%20del%20mercado%20de%20trabajo%20andaluz%20y%20dar%20informaci%26oacute%3Bn%20para%20la%20elaboraci%26oacute%3Bn%20de%20pol%26iacute%3Bticas%20de%20empleo%3Cbr%20%2F%3E%0AAs%26iacute%3B%2C%20su%20finalidad%20principal%20es%20obtener%20datos%20de%20la%20fuerza%20de%20trabajo%20y%20de%20sus%20diversas%20categor%26iacute%3Bas%20(ocupados%2C%20parados)%2C%20as%26iacute%3B%20como%20de%20la%20poblaci%26oacute%3Bn%20ajena%20al%20mercado%20laboral%20(inactivos).%20La%20muestra%20inicial%20es%20de%2065.000%20familias%20al%20trimestre%2C%20quedando%20reducida%20en%20la%20pr%26aacute%3Bctica%20a%20aproximadamente%2060.000%20familias%20entrevistadas%20de%20manera%20efectiva%20que%20equivalen%20a%20unas%20200.000%20personas%3C%2Fp%3E%0A"}}, {"id": "R13", "texts": {"es": "%3Cp%20style%3D%22text-align%3Ajustify%22%3E-%20Clasificaci%26oacute%3Bn%20Nacional%20de%20Educaci%26oacute%3Bn%202000%3Cbr%20%2F%3E%0Ahttps%3A%2F%2Fwww.ine.es%2Fdyngs%2FINEbase%2Fes%2Foperacion.htm%3Fc%3DEstadistica_C%26amp%3Bcid%3D1254736177034%26amp%3Bmenu%3Denlaces%26amp%3Bidp%3D1254735976614%3Cbr%20%2F%3E%0A%26ndash%3B%20Clasificaci%26oacute%3Bn%20Nacional%20de%20Educaci%26oacute%3Bn%202014%3Cbr%20%2F%3E%0Ahttp%3A%2F%2Fwww.ine.es%2Fdyngs%2FINEbase%2Fes%2Foperacion.htm%3Fc%3DEstadistica_C%26amp%3Bcid%3D1254736177034%26amp%3Bmenu%3DultiDatos%26amp%3Bidp%3D1254735976614%3Cbr%20%2F%3E%0A-%20Clasificaci%26oacute%3Bn%20Nacional%20de%20Actividades%20Econ%26oacute%3Bmicas%201993.%20Revisi%26oacute%3Bn%201%3Cbr%20%2F%3E%0Ahttps%3A%2F%2Fwww.ine.es%2Fdyngs%2FINEbase%2Fes%2Foperacion.htm%3Fc%3DEstadistica_C%26amp%3Bcid%3D1254736177032%26amp%3Bmenu%3Denlaces%26amp%3Bidp%3D1254735976614%3Cbr%20%2F%3E%0A-%20Clasificaci%26oacute%3Bn%20Nacional%20de%20Actividades%20Econ%26oacute%3Bmicas%202009%3Cbr%20%2F%3E%0Ahttps%3A%2F%2Fwww.ine.es%2Fdyngs%2FINEbase%2Fes%2Foperacion.htm%3Fc%3DEstadistica_C%26amp%3Bcid%3D1254736177032%26amp%3Bmenu%3DultiDatos%26amp%3Bidp%3D1254735976614%3Cbr%20%2F%3E%0A-%20Clasificaci%26oacute%3Bn%20Nacional%20de%20Ocupaciones%201994%3Cbr%20%2F%3E%0Ahttps%3A%2F%2Fwww.ine.es%2Fdyngs%2FINEbase%2Fes%2Foperacion.htm%3Fc%3DEstadistica_C%26amp%3Bcid%3D1254736177033%26amp%3Bmenu%3Denlaces%26amp%3Bidp%3D1254735976614%3Cbr%20%2F%3E%0A-%20Clasificaci%26oacute%3Bn%20Nacional%20de%20Ocupaciones%202011%3Cbr%20%2F%3E%0Ahttps%3A%2F%2Fwww.ine.es%2Fdyngs%2FINEbase%2Fes%2Foperacion.htm%3Fc%3DEstadistica_C%26amp%3Bcid%3D1254736177033%26amp%3Bmenu%3DultiDatos%26amp%3Bidp%3D1254735976614%3C%2Fp%3E%0A"}}, {"id": "R14", "texts": {"es": "%3Cp%20style%3D%22text-align%3Ajustify%22%3ECubre%20todos%20los%20sectores%20econ%26oacute%3Bmicos%20de%20la%20CNAE-09%2C%20todos%20los%20sectores%20de%20ocupaci%26oacute%3Bn%20de%20la%20CNO-11%20y%20todos%20los%20niveles%20de%20formaci%26oacute%3Bn%20alcanzado%20de%20la%20CNED-2000.%3C%2Fp%3E%0A"}}, {"id": "R15", "texts": {"es": "%3Cp%20style%3D%22text-align%3Ajustify%22%3E-%20Poblaci%26oacute%3Bn%20econ%26oacute%3Bmicamente%20activa%3A%20es%20el%20conjunto%20de%20personas%20de%20unas%20edades%20determinadas%20que%2C%20en%20un%20per%26iacute%3Bodo%20de%20referencia%20dado%2C%20suministran%20mano%20de%20obra%20para%20la%20producci%26oacute%3Bn%20de%20bienes%20y%20servicios%20econ%26oacute%3Bmicos%20o%20que%20est%26aacute%3Bn%20disponibles%20y%20hacen%20gestiones%20para%20incorporarse%20a%20dicha%20producci%26oacute%3Bn.%20En%20la%20EPA%20la%20poblaci%26oacute%3Bn%20econ%26oacute%3Bmicamente%20activa%20comprende%20todas%20las%20personas%20de%2016%20o%20m%26aacute%3Bs%20a%26ntilde%3Bos%20que%20durante%20la%20semana%20de%20referencia%20(la%20anterior%20a%20aqu%26eacute%3Blla%20en%20que%20corresponde%20realizar%20la%20entrevista%20seg%26uacute%3Bn%20el%20calendario)%20satisfacen%20las%20condiciones%20necesarias%20para%20su%20inclusi%26oacute%3Bn%20entre%20las%20personas%20ocupadas%20o%20paradas%3Cbr%20%2F%3E%0A-%20Ocupados%3A%20son%20las%20personas%20de%2016%20y%20m%26aacute%3Bs%20a%26ntilde%3Bos%20que%20durante%20la%20semana%20de%20referencia%20han%20tenido%20un%20trabajo%20por%20cuenta%20ajena%20(asalariados)%20o%20ejercido%20una%20actividad%20por%20cuenta%20propia%2C%20pudiendo%20haber%20estado%20durante%20dicha%20semana%3A%20trabajando%20al%20menos%20una%20hora%20a%20cambio%20de%20un%20sueldo%2C%20salario%2C%20beneficio%20empresarial%20o%20ganancia%20familiar%2C%20en%20met%26aacute%3Blico%20o%20en%20especie%20o%20con%20empleo%20pero%20sin%20trabajar%2C%20es%20decir%2C%20ausentes%20de%20su%20trabajo%20pero%20manteniendo%20un%20fuerte%20v%26iacute%3Bnculo%20con%20%26eacute%3Bl.%20La%20fuerza%20de%20este%20v%26iacute%3Bnculo%20se%20determina%20de%20acuerdo%20con%20la%20creencia%20del%20entrevistado%20en%20reincorporarse%20o%20no%20a%20la%20empresa%20y%20con%20la%20percepci%26oacute%3Bn%20o%20no%20de%20alg%26uacute%3Bn%20tipo%20de%20remuneraci%26oacute%3Bn%3Cbr%20%2F%3E%0A-%20Parados%3A%20se%20considerar%26aacute%3Bn%20paradas%20todas%20las%20personas%20de%2016%20o%20m%26aacute%3Bs%20a%26ntilde%3Bos%20que%20durante%20la%20semana%20de%20referencia%20hayan%20estado%20simult%26aacute%3Bneamente%3A%20sin%20trabajo%2C%20es%20decir%2C%20que%20no%20hayan%20tenido%20un%20empleo%20por%20cuenta%20ajena%20o%20por%20cuenta%20propia%20durante%20la%20semana%20de%20referencia%2C%20en%20busca%20de%20trabajo%2C%20es%20decir%2C%20que%20hayan%20tomado%20medidas%20concretas%20para%20buscar%20un%20trabajo%20por%20cuenta%20ajena%20o%20hayan%20hecho%20gestiones%20para%20establecerse%20por%20su%20cuenta%20durante%20el%20mes%20precedente%20y%20disponibles%20para%20trabajar%2C%20es%20decir%2C%20en%20condiciones%20de%20comenzar%20a%20hacerlo%20en%20un%20plazo%20de%20dos%20semanas%20a%20partir%20del%20domingo%20de%20la%20semana%20de%20referencia%3C%2Fp%3E%0A%0A%3Cp%20style%3D%22text-align%3Ajustify%22%3E%26nbsp%3B%3C%2Fp%3E%0A"}}, {"id": "R16", "texts": {"es": "%3Cp%20style%3D%22text-align%3Ajustify%22%3EPoblaci%26oacute%3Bn%20que%20reside%20en%20viviendas%20familiares%20principales%20y%20que%20ha%20formado%20parte%20de%20la%20muestra%20de%20las%20viviendas%20seleccionadas%20a%20partir%20del%20fichero%20de%20microdatos%20que%20facilita%20el%20INE.%3C%2Fp%3E%0A"}}, {"id": "R17", "texts": {"es": "%3Cp%20style%3D%22text-align%3Ajustify%22%3ELa%20Encuesta%20de%20Poblaci%26oacute%3Bn%20Activa%20va%20dirigida%20a%20la%20poblaci%26oacute%3Bn%20que%20reside%20en%20viviendas%20familiares%20principales%2C%20es%20decir%2C%20las%20utilizadas%20todo%20el%20a%26ntilde%3Bo%20o%20la%20mayor%20parte%20de%20%26eacute%3Bl%20como%20vivienda%20habitual%20o%20permanente.%20En%20el%20caso%20de%20la%20actividad%20que%20nos%20ocupa%2C%20ser%26aacute%3B%20por%20tanto%20la%20poblaci%26oacute%3Bn%20que%20reside%20en%20viviendas%20familiares%20principales%20en%20Andaluc%26iacute%3Ba.%3C%2Fp%3E%0A"}}, {"id": "R18", "texts": {"es": "Andaluc%C3%ADa"}}, {"id": "R19", "texts": {"es": "%3Cp%20style%3D%22text-align%3Ajustify%22%3ELa%20Encuesta%20de%20Poblaci%26oacute%3Bn%20Activa%20(EPA)%20es%20una%20investigaci%26oacute%3Bn%20continua%20y%20de%20periodicidad%20trimestral%20dirigida%20a%20las%20familias%2C%20realizada%20por%20el%20INE%20desde%201964.%20Su%20finalidad%20principal%20es%20obtener%20datos%20de%20la%20fuerza%20de%20trabajo%20y%20de%20sus%20diversas%20categor%26iacute%3Bas%20(ocupados%2C%20parados)%2C%20as%26iacute%3B%20como%20de%20la%20poblaci%26oacute%3Bn%20ajena%20al%20mercado%20laboral%20(inactivos).%20La%20muestra%20inicial%20es%20de%2065.000%20familias%20al%20trimestre%2C%20quedando%20reducida%20en%20la%20pr%26aacute%3Bctica%20a%20aproximadamente%2060.000%20familias%20entrevistadas%20de%20manera%20efectiva%20que%20equivalen%20a%20unas%20200.000%20personas.%3C%2Fp%3E%0A"}}, {"id": "R20", "texts": {"es": "--"}}]}}, {"id": "D", "attributeSet": {"reportedAttributes": [{"id": "R21", "texts": {"es": "%3Cp%20style%3D%22text-align%3Ajustify%22%3EPara%20los%20datos%20referidos%20a%20personas%2C%20la%20unidad%20de%20medida%20que%20se%20utiliza%20viene%20expresada%20en%20miles%20de%20personas.%3Cbr%20%2F%3E%0APara%20los%20datos%20referidos%20a%20n%26uacute%3Bmero%20de%20viviendas%2C%20la%20unidad%20de%20medida%20utilizada%20viene%20expresada%20en%20miles%20de%20viviendas.%3Cbr%20%2F%3E%0APara%20los%20indicadores%20relativos%20a%20tasas%20y%20distribuciones%20relativas%2C%20el%20porcentaje%20es%20la%20unidad%20de%20medida%20utilizada.%3C%2Fp%3E%0A"}}]}}, {"id": "E", "attributeSet": {"reportedAttributes": [{"id": "R22", "texts": {"es": "%3Cp%20style%3D%22text-align%3Ajustify%22%3ETri4%2F2019%2C%20Tri1%2F2020%2C%20Tri2%2F2020%2C%20Tri3%2F2020%2C%202019%2C%202019%2C%202019%3C%2Fp%3E%0A"}}]}}, {"id": "F", "attributeSet": {"reportedAttributes": [{"id": "R23", "texts": {"es": "%3Cp%20style%3D%22text-align%3Ajustify%22%3ELey%204%2F1989%2C%20de%2012%20de%20diciembre%2C%20de%20Estad%26iacute%3Bstica%20de%20la%20Comunidad%20Aut%26oacute%3Bnoma%20de%20Andaluc%26iacute%3Ba%3Cbr%20%2F%3E%0ALey%203%2F2013%2C%20de%2024%20de%20julio%2C%20por%20la%20que%20se%20aprueba%20el%20Plan%20Estad%26iacute%3Bstico%20y%20Cartogr%26aacute%3Bfico%20de%20Andaluc%26iacute%3Ba%202013-2017%20y%20Ley%206%2F2017%2C%20de%2027%20de%20diciembre%2C%20por%20la%20que%20se%20modifica%20la%20Ley%203%2F2013%2C%20de%2024%20de%20julio%2C%20por%20la%20que%20se%20aprueba%20el%20Plan%20Estad%26iacute%3Bstico%20y%20Cartogr%26aacute%3Bfico%20de%20Andaluc%26iacute%3Ba%202013-2017%20para%20ampliar%20su%20vigencia%20hasta%20el%202020%3Cbr%20%2F%3E%0ADecreto%2025%2F2020%2C%20de%2024%20de%20febrero%2C%20por%20el%20que%20se%20aprueba%20el%20Programa%20Estad%26iacute%3Bstico%20y%20Cartogr%26aacute%3Bfico%20de%20la%20Comunidad%20Aut%26oacute%3Bnoma%20de%20Andaluc%26iacute%3Ba%20para%20el%20a%26ntilde%3Bo%202020%3C%2Fp%3E%0A"}}, {"id": "R24", "texts": {"es": "%3Cp%20style%3D%22text-align%3Ajustify%22%3EAcuerdo%20Marco%20sobre%20cooperaci%26oacute%3Bn%20estad%26iacute%3Bstica%20e%20intercambio%20de%20informaci%26oacute%3Bn%20entre%20el%20Instituto%20Nacional%20de%20Estad%26iacute%3Bstica%20y%20el%20Instituto%20de%20Estad%26iacute%3Bstica%20de%20Andaluc%26iacute%3Ba.%3C%2Fp%3E%0A"}}]}}, {"id": "G", "attributeSet": {"reportedAttributes": [{"id": "R25", "texts": {"es": "%3Cul%3E%0A%09%3Cli%3ELey%204%2F1989%2C%20de%2012%20de%20diciembre%2C%20de%20Estad%26iacute%3Bstica%20de%20la%20Comunidad%20Aut%26oacute%3Bnoma%20de%20Andaluc%26iacute%3Ba%3C%2Fli%3E%0A%09%3Cli%3ELey%2012%2F1989%2C%20de%209%20de%20mayo%2C%20de%20la%20Funci%26oacute%3Bn%20Estad%26iacute%3Bstica%20P%26uacute%3Bblica%3C%2Fli%3E%0A%09%3Cli%3ELey%20Org%26aacute%3Bnica%203%2F2018%2C%20de%205%20de%20diciembre%2C%20de%20Protecci%26oacute%3Bn%20de%20Datos%20Personales%20y%20garant%26iacute%3Ba%20de%20los%20derechos%20digitales%3C%2Fli%3E%0A%3C%2Ful%3E%0A"}}, {"id": "R26", "texts": {"es": "%3Cp%20style%3D%22text-align%3Ajustify%22%3ELos%20ficheros%20de%20microdatos%20recibidos%20por%20el%20INE%20est%26aacute%3Bn%20anonimizados%20y%20la%20desagregaci%26oacute%3Bn%20m%26aacute%3Bxima%20alcanzada%20en%20la%20difusi%26oacute%3Bn%20no%20permiten%20la%20identificaci%26oacute%3Bn%20directa%20o%20indirecta%20de%20las%20personas%20entrevistadas%20por%20el%20INE%3C%2Fp%3E%0A"}}]}}, {"id": "H", "attributeSet": {"reportedAttributes": [{"id": "R27", "texts": {"es": "28%2F01%2F2020%2C%2028%2F04%2F2020%2C%2028%2F07%2F2020%2C%2027%2F10%2F2020%2C%2007%2F02%2F2020%2C%2007%2F04%2F2020%2C%2023%2F12%2F2020"}}, {"id": "R28", "texts": {"es": "Ene%2F2020%2C%20Abr%2F2020%2C%20Jul%2F2020%2C%20Oct%2F2020%2C%20Feb%2F2020%2C%20May%2F2020%2C%20Dic%2F2020"}}, {"id": "R29", "texts": {"es": "%3Cp%20style%3D%22text-align%3Ajustify%22%3ELa%20actividad%20se%20difunde%20a%20trav%26eacute%3Bs%20de%20la%20p%26aacute%3Bgina%20web%20del%20IECA.%20La%20informaci%26oacute%3Bn%20se%20ofrece%20en%20formato%20excel%20a%20trav%26eacute%3Bs%20de%20un%20%26aacute%3Brbol%20tem%26aacute%3Btico%20y%20a%20trav%26eacute%3Bs%20de%20la%20base%20de%20datos%20BADEA%3Cbr%20%2F%3E%0APara%20el%20producto%20de%20la%20Encuesta%20de%20Poblaci%26oacute%3Bn%20activa%3A%3Cbr%20%2F%3E%0Ahttp%3A%2F%2Fwww.juntadeandalucia.es%2Finstitutodeestadisticaycartografia%2Fepa%2Findex.htm%3Cbr%20%2F%3E%0APara%20el%20producto%20%26quot%3BEl%20empleo%20de%20las%20personas%20discapacitadas%26quot%3B%3A%3Cbr%20%2F%3E%0Ahttp%3A%2F%2Fwww.juntadeandalucia.es%2Finstitutodeestadisticaycartografia%2Fepd%2Findex.htm%3C%2Fp%3E%0A"}}]}}, {"id": "I", "attributeSet": {"reportedAttributes": [{"id": "R30", "texts": {"es": "Anual%2C%20Trimestral"}}]}}, {"id": "J", "attributeSet": {"reportedAttributes": [{"id": "R31", "texts": {"es": "%3Cp%20style%3D%22text-align%3Ajustify%22%3ES%26iacute%3B%3Cbr%20%2F%3E%0Ahttp%3A%2F%2Fwww.juntadeandalucia.es%2Finstitutodeestadisticaycartografia%2Fepa%2Findex.htm%3C%2Fp%3E%0A"}}, {"id": "R32", "texts": {"es": "Encuesta%20de%20Poblaci%C3%B3n%20Activa%0AEl%20empleo%20de%20las%20personas%20con%20discapacidad"}}, {"id": "R33", "texts": {"es": "Esta%20actividad%20permite%20elaborar%20resultados%20a%20medida%20en%20el%20Banco%20de%20Datos%20estad%C3%ADstico%20de%20Andaluc%C3%ADa%20(BADEA)"}}, {"id": "R34", "texts": {"es": "No%20existe%20disponibilidad%20de%20microdatos%20para%20esta%20actividad"}}, {"id": "R35", "texts": {"es": "--"}}]}}, {"id": "K", "attributeSet": {"reportedAttributes": [{"id": "R36", "texts": {"es": "La%20memoria%20t%C3%A9cnica%20est%C3%A1%20disponible%20en%20Internet%20en%20el%20apartado%20Metodolog%C3%ADa"}}, {"id": "R37", "texts": {"es": "El%20IECA%20para%20garantizar%20la%20calidad%20en%20esta%20actividad%20aporta%20la%20memoria%20t%C3%A9cnica%2C%20la%20ficha%20de%20indicadores%20de%20calidad%20y%20el%20informe%20metodol%C3%B3gico%20estandarizado%20de%20la%20actividad."}}]}}, {"id": "L", "attributeSet": {"reportedAttributes": [{"id": "R38", "texts": {"es": "%3Cp%20style%3D%22text-align%3Ajustify%22%3EAl%20tratarse%20de%20una%20encuesta%2C%20la%20calidad%20de%20los%20datos%20est%26aacute%3Bn%20afectados%20del%20error%20de%20muestreo%2C%20siendo%20%26eacute%3Bste%2C%20por%20tanto%2C%20el%20criterio%20base%20para%20definir%20qu%26eacute%3B%20informaci%26oacute%3Bn%20difundir.%20En%20el%20caso%20de%20que%20explotaci%26oacute%3Bn%20espec%26iacute%3Bfica%20se%20vea%20afectada%20en%20m%26aacute%3Bs%20de%20un%2020%25%20por%20fuertes%20errores%20de%20muestreo%20(valores%20en%20celdas%20inferiores%20a%205.000%20personas)%20la%20tabla%20no%20se%20publicar%26aacute%3B.%20Y%2C%20en%20aquellas%20tablas%20afectadas%20en%20menos%20del%2020%25%2C%20se%20publicar%26aacute%3Bn%20indicando%20a%20pie%20de%20tabla%20que%20los%20dichos%20datos%20deben%20ser%20tomados%20con%20precauci%26oacute%3Bn%20debido%20a%20la%20fuerte%20variabilidad%20a%20la%20que%20pueden%20estar%20sometidos.%3C%2Fp%3E%0A"}}, {"id": "R39", "texts": {"es": "Se%20ha%20elaborado%20una%20ficha%20de%20calidad%20y%20est%C3%A1%20disponible%20en%20Internet%20en%20el%20apartado%20Metodolog%C3%ADa."}}]}}, {"id": "M", "attributeSet": {"reportedAttributes": [{"id": "R40", "texts": {"es": "Administraci%C3%B3n%2C%20investigadores%2C%20organizaciones%20sindicales%2C%20periodistas."}}, {"id": "R41", "texts": {"es": "--"}}, {"id": "R42", "texts": {"es": "%3Cp%20style%3D%22text-align%3Ajustify%22%3ELa%20poblaci%26oacute%3Bn%20de%20estudio%20es%20la%20poblaci%26oacute%3Bn%20que%20reside%20en%20viviendas%20familiares%20principales%20quedando%20fuera%20del%20an%26aacute%3Blisis%20las%20personas%20que%20residen%20en%20los%20llamados%20hogares%20colectivos%20(hospitales%2C%20residencias%2C%20cuarteles...)%20que%20representan%20menos%20del%20uno%20por%20ciento%20de%20la%20poblaci%26oacute%3Bn.%3Cbr%20%2F%3E%0ALa%20restricci%26oacute%3Bn%20fundamental%20es%20metodol%26oacute%3Bgica%20debido%20a%20los%20errores%20de%20muestreo%2C%20lo%20que%20obliga%20a%20valorar%20los%20niveles%20de%20significaci%26oacute%3Bn%20de%20la%20informaci%26oacute%3Bn%20que%20se%20difunda.%20A%20medida%20que%20se%20desagrega%20m%26aacute%3Bs%20la%20informaci%26oacute%3Bn%2C%20ya%20sea%20por%20detallar%20los%20valores%20de%20las%20de%20variables%2C%20por%20realizar%20desagregaciones%20territoriales%20o%20por%20cruzar%20varias%20variables%2C%20aumentan%20los%20errores%20de%20muestreo.%20Por%20ello%2C%20y%20de%20forma%20orientativa%2C%20aquellos%20valores%20inferiores%20a%205.000%20personas%2C%20o%20las%20tasas%20e%20indicadores%20derivados%20de%20los%20mismos%2C%20est%26aacute%3Bn%20sometidos%20a%20fuertes%20errores%20de%20muestreo.%3Cbr%20%2F%3E%0APor%20tanto%2C%20la%20difusi%26oacute%3Bn%20de%20los%20datos%20de%20la%20EPA%20en%20Andaluc%26iacute%3Ba%20y%20el%20poder%20dar%20informaci%26oacute%3Bn%20de%20algunas%20caracter%26iacute%3Bsticas%20con%20mayor%20desagregraci%26oacute%3Bn%20est%26aacute%3Bn%20restringidos%20a%20los%20errores%20de%20muestreo%20derivados%20de%20su%20propia%20condici%26oacute%3Bn%20de%20encuesta%20por%20muestreo.%3C%2Fp%3E%0A"}}]}}, {"id": "N", "attributeSet": {"reportedAttributes": [{"id": "R43", "texts": {"es": "La%20recogida%20de%20informaci%C3%B3n%20de%20esta%20actividad%20se%20basa%20en%20una%20explotaci%C3%B3n%20de%20informaci%C3%B3n%20estad%C3%ADstica%20oficial%2C%20ello%20permite%20asegurar%20que%20en%20el%20desarrollo%20de%20las%20mismas%20se%20ha%20realizado%20un%20estudio%20de%20fiabilidad%20por%20lo%20que%20la%20informaci%C3%B3n%20obtenida%20a%20partir%20de%20ella%20y%20por%20lo%20tanto%20de%20la%20actividad%20es%20fiable."}}, {"id": "R44", "texts": {"es": "--"}}, {"id": "R45", "texts": {"es": "%3Cp%20style%3D%22text-align%3Ajustify%22%3E--%3C%2Fp%3E%0A"}}]}}, {"id": "O", "attributeSet": {"reportedAttributes": [{"id": "R46", "texts": {"es": "40%20d%C3%ADas%20para%20Encuesta%20de%20Poblaci%C3%B3n%20Activa%2C%0A357%20d%C3%ADas%20para%20El%20Empleo%20de%20las%20Personas%20con%20Discapacidad."}}, {"id": "R47", "texts": {"es": "-3%20d%C3%ADas%20para%20Encuesta%20de%20Poblaci%C3%B3n%20Activa%2C%0A0%20d%C3%ADas%20para%20El%20Empleo%20de%20las%20Personas%20con%20Discapacidad."}}]}}, {"id": "P", "attributeSet": {"reportedAttributes": [{"id": "R48", "texts": {"es": "%3Cp%20style%3D%22text-align%3Ajustify%22%3ELa%20actividad%20es%20una%20explotaci%26oacute%3Bn%20de%20los%20microdatos%20de%20Andaluc%26iacute%3Ba%20de%20la%20Encuesta%20de%20Poblaci%26oacute%3Bn%20Activa%20realizada%20por%20el%20INE%2C%20ello%20nos%20confirma%20que%20la%20comparabilidad%20a%20tanto%20a%20nivel%20nacional%2C%20como%20a%20nivel%20regional%20es%20total.%3C%2Fp%3E%0A"}}, {"id": "R49", "texts": {"es": "%3Cp%20style%3D%22text-align%3Ajustify%22%3ELa%20EPA%20ha%20sufrido%20varias%20modificaciones%20desde%20el%20a%26ntilde%3Bo%201964%2C%20siendo%20las%20dos%20m%26aacute%3Bs%20recientes%20las%20siguientes%3A%3Cbr%20%2F%3E%0ALa%20modificaci%26oacute%3Bn%20que%20se%20realiz%26oacute%3B%20en%202002.%20Los%20cambios%20metodol%26oacute%3Bgicos%20afectaron%20a%20algunas%20de%20las%20definiciones%20utilizadas%20en%20la%20encuesta%20y%20al%20proceso%20de%20c%26aacute%3Blculo%20de%20resultados%3A%3Cbr%20%2F%3E%0Aa)%20Se%20utilizan%20las%20nuevas%20proyecciones%20de%20poblaci%26oacute%3Bn%20del%20INE.%3Cbr%20%2F%3E%0Ab)%20Se%20introduce%20una%20mejora%20t%26eacute%3Bcnica%20en%20el%20c%26aacute%3Blculo%20de%20totales%20(reponderaci%26oacute%3Bn%20de%20los%20factores%20de%20elevaci%26oacute%3Bn).%3Cbr%20%2F%3E%0Ac)%20Por%20%26uacute%3Bltimo%2C%20aunque%20la%20definici%26oacute%3Bn%20formal%20de%20paro%20no%20cambia%20el%20nuevo%20Reglamento%20(CE)%20N%26ordm%3B%201897%2F2000%20de%20la%20Comisi%26oacute%3Bn%2C%20de%207%20de%20septiembre%20de%202000%2C%20introduce%20instrucciones%20sobre%20c%26oacute%3Bmo%20interpretar%20la%20b%26uacute%3Bsqueda%20activa%20de%20trabajo.%3Cbr%20%2F%3E%0AEl%20primero%20de%20estos%20cambios%20est%26aacute%3B%20originado%20por%20el%20incremento%20que%20se%20ha%20producido%20en%20la%20poblaci%26oacute%3Bn%20espa%26ntilde%3Bola%20como%20resultado%20de%20la%20llegada%20de%20inmigrantes.%20El%20segundo%20es%20una%20mejora%20en%20la%20forma%20de%20corregir%20el%20efecto%20de%20la%20falta%20de%20respuesta%20en%20la%20encuesta.%20El%20tercero%20viene%20regulado%20por%20la%20Oficina%20Estad%26iacute%3Bstica%20de%20la%20Uni%26oacute%3Bn%20Europea%20(Eurostat).%3Cbr%20%2F%3E%0ALas%20repercusiones%20de%20estos%20cambios%20en%20las%20estimaciones%20de%20la%20encuesta%20fueron%20importantes%20produciendo%20una%20ruptura%20en%20la%20comparaci%26oacute%3Bn%20de%20los%20datos%20a%20partir%20de%20esa%20fecha.%20Para%20solventar%20las%20discontinuidades%20en%20las%20series%20de%20los%20resultados%20de%20forma%20que%20fuera%20posible%20cuantificar%20la%20evoluci%26oacute%3Bn%20del%20mercado%20laboral%20doblemente%2C%20con%20los%20efectos%20de%20las%20modificaciones%20y%20sin%20sus%20repercusiones%2C%20el%20INE%20elabor%26oacute%3B%20un%20proceso%20cuya%20informaci%26oacute%3Bn%20puede%20encontrase%20en%20la%20p%26aacute%3Bgina%20del%20INE%20(www.ine.es).%3Cbr%20%2F%3E%0ANo%20obstante%20es%20necesario%20se%26ntilde%3Balar%20que%20la%20aplicaci%26oacute%3Bn%20de%20las%20instrucciones%20sobre%20la%20b%26uacute%3Bsqueda%20activa%20de%20trabajo%20en%20la%20definici%26oacute%3Bn%20de%20paro%20introduc%26iacute%3Ba%20una%20ruptura%20en%20las%20series.%3Cbr%20%2F%3E%0APor%20este%20motivo%20el%20INE%20realiz%26oacute%3B%20un%20procedimiento%20basado%20en%20%26quot%3Bregresi%26oacute%3Bn%20con%20variable%26quot%3B%20para%20el%20enlace%20de%20series%20de%20paro%20que%20salva%20la%20discontinuidad%20producida%20en%20dichas%20series%20por%20el%20cambio%20de%20definici%26oacute%3Bn%20ocurrido%20en%20el%20a%26ntilde%3Bo%202002.%20El%20enlace%20se%20extiende%20desde%20el%20tercer%20trimestre%20de%201976%20hasta%20el%20cuarto%20trimestre%20de%202000%20y%20se%20ha%20realizado%20para%20los%20principales%20agregados%20(paro%20por%20sexo%20y%20edad%20menor%20de%2025%20a%26ntilde%3Bos%20%26oacute%3B%2025%20a%26ntilde%3Bos%20y%20m%26aacute%3Bs)%20a%20nivel%20nacional%20y%20por%20comunidades%20aut%26oacute%3Bnomas.%3Cbr%20%2F%3E%0ALa%20%26uacute%3Bltima%20modificaci%26oacute%3Bn%20en%20la%20metodolog%26iacute%3Ba%20de%20la%20encuesta%20se%20realiz%26oacute%3B%20en%20el%20primer%20trimestre%20de%202005%20por%20varias%20causas%3A%20la%20necesidad%20de%20adecuarse%20a%20la%20nueva%20realidad%20demogr%26aacute%3Bfica%20y%20laboral%20de%20nuestro%20pa%26iacute%3Bs%2C%20debida%20especialmente%20al%20aumento%20del%20n%26uacute%3Bmero%20de%20extranjeros%20residentes%3B%20la%20incorporaci%26oacute%3Bn%20de%20la%20nueva%20normativa%20europea%20siguiendo%20las%20normas%20de%20la%20Oficina%20Estad%26iacute%3Bstica%20de%20la%20Uni%26oacute%3Bn%20Europea%20(Eurostat)%3B%20y%20por%20%26uacute%3Bltimo%2C%20la%20introducci%26oacute%3Bn%20de%20mejoras%20en%20el%20m%26eacute%3Btodo%20de%20recogida.%3Cbr%20%2F%3E%0AFinalmente%2C%20la%20base%20poblacional%20utilizada%20a%20partir%20del%20primer%20trimestre%20de%202005%20(base%20poblacional%20censo%202001)%20es%20la%20misma%20con%20la%20que%20se%20ha%20calculado%20la%20serie%201996-2004%20(revisada%20el%2030%20de%20marzo%20de%202005)%2C%20existiendo%2C%20por%20tanto%2C%20continuidad%20en%20la%20serie%3Cbr%20%2F%3E%0ALa%20base%20poblacional%20utilizada%20actualmente%20es%20la%20del%20censo%20de%20poblaci%26oacute%3Bn%20de%202011.%20Los%20datos%20de%20la%20encuesta%20del%20periodo%202002-2013%20se%20revisaron%20el%2024%20de%20abril%20de%202014%20teniendo%20en%20cuenta%20la%20nueva%20base%20poblacional.%3C%2Fp%3E%0A"}}]}}, {"id": "Q", "attributeSet": {"reportedAttributes": [{"id": "R50", "texts": {"es": "%3Cp%20style%3D%22text-align%3Ajustify%22%3ELa%20informaci%26oacute%3Bn%20contenida%20en%20la%20actividad%20es%20coherente%20con%20la%20contenida%20en%20el%20mismo%20sector%20y%20en%20el%20mismo%20%26aacute%3Bmbito%20como%20es%20el%20sistema%20de%20informaci%26oacute%3Bn%20del%20mercado%20de%20trabajo%20andaluz%20realizado%20por%20el%20IECA%2C%20la%20estad%26iacute%3Bstica%20de%20empleo%20en%20Andaluc%26iacute%3Ba%2C%20la%20estad%26iacute%3Bstica%20sobre%20discapacidad%20y%20mercado%20laboral%20en%20Andaluc%26iacute%3Ba%20y%20la%20estad%26iacute%3Bstica%20de%20empleo%20en%20Andaluc%26iacute%3Ba%20realizada%20por%20el%20SAE%20o%20los%20Afiliados%20a%20la%20Seguridad%20Social.%3C%2Fp%3E%0A"}}, {"id": "R51", "texts": {"es": "La%20coherencia%20interna%20se%20garantiza%20a%20trav%C3%A9s%20de%20diversas%20validaciones%20realizadas%20antes%20de%20la%20publicaci%C3%B3n%20de%20los%20datos."}}]}}, {"id": "R", "attributeSet": {"reportedAttributes": [{"id": "R52", "texts": {"es": "9.000%2C00%20%E2%82%AC"}}]}}, {"id": "S", "attributeSet": {"reportedAttributes": [{"id": "R53", "texts": {"es": "%3Cp%20style%3D%22text-align%3Ajustify%22%3EAl%20no%20existir%20datos%20provisionales%20no%20se%20realiza%20una%20revisi%26oacute%3Bn%20de%20los%20datos.%3C%2Fp%3E%0A"}}, {"id": "R54", "texts": {"es": "%3Cp%3E--%3C%2Fp%3E%0A"}}]}}, {"id": "T", "attributeSet": {"reportedAttributes": [{"id": "R55", "texts": {"es": "Explotaci%C3%B3n%20de%20informaci%C3%B3n%20estad%C3%ADstica%20o%20cartogr%C3%A1fica."}}, {"id": "R56", "texts": {"es": "Trimestral%2C%20Anual."}}, {"id": "R57", "texts": {"es": "%3Cp%20style%3D%22text-align%3Ajustify%22%3ELa%20informaci%26oacute%3Bn%20base%2C%20es%20decir%2C%20los%20microdatos%20de%20la%20Encuesta%20de%20Poblaci%26oacute%3Bn%20Activa%20de%20la%20Comunidad%20Aut%26oacute%3Bnoma%20de%20Andaluc%26iacute%3Ba%2C%20se%20reciben%20en%20el%20Instituto%20de%20Estad%26iacute%3Bstica%20y%20Cartograf%26iacute%3Ba%20de%20Andaluc%26iacute%3Ba%20a%20trav%26eacute%3Bs%20del%20Instituto%20Nacional%20de%20Estad%26iacute%3Bstica%2C%20el%20mismo%20d%26iacute%3Ba%20que%20seg%26uacute%3Bn%20el%20calendario%20del%20INE%20se%20dan%20a%20conocer%20los%20resultados%20trimestrales%20de%20la%20Encuesta.%3Cbr%20%2F%3E%0ALos%20microdatos%20recibidos%20pasan%20por%20un%20proceso%20de%20recodificaci%26oacute%3Bn%20y%20reestructuraci%26oacute%3Bn%20para%20tener%20cabida%20en%20la%20base%20de%20datos%20BADEA%2C%20a%20trav%26eacute%3Bs%20de%20la%20que%20se%20realiza%20el%20proceso%20de%20tabulaci%26oacute%3Bn%20y%20difusi%26oacute%3Bn.%3C%2Fp%3E%0A"}}, {"id": "R58", "texts": {"es": "%3Cp%20style%3D%22text-align%3Ajustify%22%3E--%3C%2Fp%3E%0A"}}, {"id": "R59", "texts": {"es": "%3Cp%20style%3D%22text-align%3Ajustify%22%3EEl%20plan%20de%20an%26aacute%3Blisis%20elaborado%20por%20el%20IECA%2C%20se%20centra%20en%20dos%20an%26aacute%3Blisis%20y%20momentos%20distintos%3A%3Cbr%20%2F%3E%0AUn%20primer%20an%26aacute%3Blisis%20de%20la%20informaci%26oacute%3Bn%20es%20de%20car%26aacute%3Bcter%20coyuntural%20que%20ofrece%20resultados%20trimestrales.%20Se%20trata%20de%20ofrecer%20con%20la%20mayor%20brevedad%20posible%20informaci%26oacute%3Bn%20detallada%20de%20car%26aacute%3Bcter%20coyuntural%20centrada%20en%20los%20aspectos%20m%26aacute%3Bs%20importantes%20del%20mercado%20de%20trabajo%20y%20de%20facilitar%20el%20an%26aacute%3Blisis%20r%26aacute%3Bpido%20de%20%26eacute%3Bsta%20mediante%20la%20inclusi%26oacute%3Bn%20de%20indicadores%20y%20del%20c%26aacute%3Blculo%20de%20variaciones%20entre%20trimestres%20consecutivos%20as%26iacute%3B%20como%20variaciones%20interanuales.%20En%20este%20primer%20informe%20se%20presentar%26aacute%3Bn%20tambi%26eacute%3Bn%20los%20resultados%20nacionales%2C%20con%20sus%20correspondientes%20indicadores%20y%20variaciones%2C%20que%20faciliten%20la%20comparabilidad%20de%20la%20coyuntura%20del%20mercado%20laboral%20andaluz%20con%20la%20coyuntura%20del%20mercado%20laboral%20nacional.%3Cbr%20%2F%3E%0AAdem%26aacute%3Bs%2C%20incluir%26aacute%3B%20informaci%26oacute%3Bn%20provincial%20algo%20menos%20detallada%20que%20la%20dada%20para%20el%20total%20de%20Andaluc%26iacute%3Ba%20debido%20a%20que%20la%20representatividad%20muestral%20de%20las%20provincias%20no%20permite%20tanta%20desagregaci%26oacute%3Bn.%3Cbr%20%2F%3E%0AEl%20segundo%20an%26aacute%3Blisis%20pretende%20dar%20una%20visi%26oacute%3Bn%20m%26aacute%3Bs%20estructural%2C%20analizando%20lo%20ocurrido%20en%20el%20mercado%20laboral%20andaluz%20en%20el%20%26uacute%3Bltimo%20a%26ntilde%3Bo%20natural.%20En%20esta%20ocasi%26oacute%3Bn%2C%20la%20filosof%26iacute%3Ba%20del%20plan%20de%20an%26aacute%3Blisis%20y%20tabulaci%26oacute%3Bn%20es%20ofrecer%20informaci%26oacute%3Bn%20m%26aacute%3Bs%20detallada%2C%20s%26oacute%3Blo%20para%20Andaluc%26iacute%3Ba%2C%20centr%26aacute%3Bndose%20m%26aacute%3Bs%20en%20explotar%20de%20forma%20ampliada%20aquellos%20aspectos%20considerados%20de%20inter%26eacute%3Bs%20que%20no%20se%20recogen%20suficientemente%20en%20las%20publicaciones%20originales%20del%20INE%2C%20y%20que%20no%20sean%20meras%20r%26eacute%3Bplicas%20de%20las%20explotaciones%20del%20%26aacute%3Bmbito%20estatal.%3C%2Fp%3E%0A"}}, {"id": "R60", "texts": {"es": "--"}}]}}, {"id": "U", "attributeSet": {"reportedAttributes": [{"id": "R61", "texts": {"es": "Metodolog%C3%ADa%20de%20la%20Encuesta%20de%20Poblaci%C3%B3n%20Activa%20realizada%20por%20el%20INE%0Ahttp%3A%2F%2Fwww.ine.es%2FinebaseDYN%2Fepa30308%2Fepa_metodologia.htm"}}]}}]}}]}]}}